{"date":"2023-09-18","hours":[{"h":0,"rides":11425,"boroughs":{"Manhattan":{"rides":3839,"avg_fare":22.5417},"Brooklyn":{"rides":3041,"avg_fare":19.0649},"Queens":{"rides":3026,"avg_fare":32.0287},"Bronx":{"rides":1407,"avg_fare":15.6638},"Staten Island":{"rides":112,"avg_fare":19.3349}},"avg_fare":23.2505,"avg_pay":20.5758,"avg_miles":6.0699,"avg_trip_time":1017.2845},{"h":1,"rides":6047,"boroughs":{"Manhattan":{"rides":2132,"avg_fare":22.2569},"Brooklyn":{"rides":1689,"avg_fare":18.073},"Queens":{"rides":1374,"avg_fare":23.9835},"Bronx":{"rides":793,"avg_fare":15.7084},"Staten Island":{"rides":59,"avg_fare":22.6092}},"avg_fare":20.6253,"avg_pay":17.2641,"avg_miles":5.472,"avg_trip_time":941.6775},{"h":2,"rides":3980,"boroughs":{"Manhattan":{"rides":1421,"avg_fare":23.3491},"Brooklyn":{"rides":1118,"avg_fare":18.5555},"Queens":{"rides":874,"avg_fare":22.0952},"Bronx":{"rides":534,"avg_fare":16.5775},"Staten Island":{"rides":33,"avg_fare":28.2703}},"avg_fare":20.8594,"avg_pay":17.2155,"avg_miles":5.6252,"avg_trip_time":942.2085},{"h":3,"rides":3556,"boroughs":{"Manhattan":{"rides":1138,"avg_fare":29.0451},"Brooklyn":{"rides":960,"avg_fare":23.0584},"Queens":{"rides":919,"avg_fare":23.6922},"Bronx":{"rides":499,"avg_fare":18.6434},"Staten Island":{"rides":40,"avg_fare":30.3772}},"avg_fare":24.6009,"avg_pay":19.4849,"avg_miles":6.5168,"avg_trip_time":1003.3954},{"h":4,"rides":5263,"boroughs":{"Manhattan":{"rides":1628,"avg_fare":41.539},"Brooklyn":{"rides":1393,"avg_fare":29.7799},"Queens":{"rides":1396,"avg_fare":24.7293},"Bronx":{"rides":766,"avg_fare":23.9419},"Staten Island":{"rides":78,"avg_fare":26.0621}},"avg_fare":31.1708,"avg_pay":22.8667,"avg_miles":7.5768,"avg_trip_time":1099.0376},{"h":5,"rides":8000,"boroughs":{"Manhattan":{"rides":2456,"avg_fare":41.4639},"Brooklyn":{"rides":1946,"avg_fare":35.588},"Queens":{"rides":2223,"avg_fare":26.1656},"Bronx":{"rides":1226,"avg_fare":23.406},"Staten Island":{"rides":149,"avg_fare":28.6347}},"avg_fare":32.7773,"avg_pay":24.6076,"avg_miles":7.5564,"avg_trip_time":1254.6979},{"h":6,"rides":14834,"boroughs":{"Manhattan":{"rides":4837,"avg_fare":38.4938},"Brooklyn":{"rides":3412,"avg_fare":38.4962},"Queens":{"rides":3894,"avg_fare":29.6759},"Bronx":{"rides":2446,"avg_fare":24.958},"Staten Island":{"rides":244,"avg_fare":26.1758}},"avg_fare":33.7433,"avg_pay":26.2924,"avg_miles":6.2582,"avg_trip_time":1373.0553},{"h":7,"rides":26026,"boroughs":{"Manhattan":{"rides":8117,"avg_fare":43.0205},"Brooklyn":{"rides":6418,"avg_fare":34.1487},"Queens":{"rides":6438,"avg_fare":30.2562},"Bronx":{"rides":4526,"avg_fare":28.5151},"Staten Island":{"rides":527,"avg_fare":24.0009}},"avg_fare":34.7676,"avg_pay":31.4262,"avg_miles":4.7801,"avg_trip_time":1439.8452},{"h":8,"rides":32226,"boroughs":{"Manhattan":{"rides":10614,"avg_fare":41.5957},"Brooklyn":{"rides":7961,"avg_fare":29.5032},"Queens":{"rides":7637,"avg_fare":28.446},"Bronx":{"rides":5371,"avg_fare":22.0896},"Staten Island":{"rides":641,"avg_fare":22.1478}},"avg_fare":31.8538,"avg_pay":27.3,"avg_miles":4.1618,"avg_trip_time":1407.57},{"h":9,"rides":26144,"boroughs":{"Manhattan":{"rides":10360,"avg_fare":29.8601},"Brooklyn":{"rides":6255,"avg_fare":24.904},"Queens":{"rides":5734,"avg_fare":31.3509},"Bronx":{"rides":3408,"avg_fare":19.4825},"Staten Island":{"rides":386,"avg_fare":21.3195}},"avg_fare":27.5217,"avg_pay":22.6777,"avg_miles":4.4091,"avg_trip_time":1424.0871},{"h":10,"rides":23452,"boroughs":{"Manhattan":{"rides":10218,"avg_fare":26.7099},"Brooklyn":{"rides":5484,"avg_fare":22.2291},"Queens":{"rides":4817,"avg_fare":32.2759},"Bronx":{"rides":2653,"avg_fare":19.112},"Staten Island":{"rides":279,"avg_fare":20.709}},"avg_fare":25.8738,"avg_pay":21.1894,"avg_miles":4.4985,"avg_trip_time":1423.5526},{"h":11,"rides":22666,"boroughs":{"Manhattan":{"rides":9325,"avg_fare":28.7503},"Brooklyn":{"rides":5735,"avg_fare":21.4213},"Queens":{"rides":4797,"avg_fare":28.8242},"Bronx":{"rides":2504,"avg_fare":18.4168},"Staten Island":{"rides":304,"avg_fare":23.5222}},"avg_fare":25.6999,"avg_pay":20.4979,"avg_miles":4.5384,"avg_trip_time":1371.6622},{"h":12,"rides":19405,"boroughs":{"Manhattan":{"rides":7597,"avg_fare":31.0844},"Brooklyn":{"rides":4972,"avg_fare":21.5569},"Queens":{"rides":4369,"avg_fare":30.1095},"Bronx":{"rides":2193,"avg_fare":18.834},"Staten Island":{"rides":273,"avg_fare":22.4401}},"avg_fare":26.918,"avg_pay":21.5548,"avg_miles":5.0553,"avg_trip_time":1414.6672},{"h":13,"rides":19863,"boroughs":{"Manhattan":{"rides":7849,"avg_fare":31.2783},"Brooklyn":{"rides":4743,"avg_fare":22.2118},"Queens":{"rides":4542,"avg_fare":30.327},"Bronx":{"rides":2417,"avg_fare":18.3903},"Staten Island":{"rides":312,"avg_fare":20.3387}},"avg_fare":27.1557,"avg_pay":21.9642,"avg_miles":5.2347,"avg_trip_time":1434.2949},{"h":14,"rides":22463,"boroughs":{"Manhattan":{"rides":8242,"avg_fare":32.7132},"Brooklyn":{"rides":5473,"avg_fare":20.93},"Queens":{"rides":5344,"avg_fare":28.1496},"Bronx":{"rides":3004,"avg_fare":17.8284},"Staten Island":{"rides":399,"avg_fare":19.182}},"avg_fare":26.5255,"avg_pay":21.6177,"avg_miles":4.873,"avg_trip_time":1442.8871},{"h":15,"rides":21600,"boroughs":{"Manhattan":{"rides":7904,"avg_fare":33.0298},"Brooklyn":{"rides":5415,"avg_fare":21.6151},"Queens":{"rides":5031,"avg_fare":32.0222},"Bronx":{"rides":2874,"avg_fare":18.6876},"Staten Island":{"rides":372,"avg_fare":20.1298}},"avg_fare":27.8016,"avg_pay":23.0004,"avg_miles":5.1145,"avg_trip_time":1545.3846},{"h":16,"rides":22160,"boroughs":{"Manhattan":{"rides":8253,"avg_fare":33.5274},"Brooklyn":{"rides":5749,"avg_fare":21.1367},"Queens":{"rides":4949,"avg_fare":31.6391},"Bronx":{"rides":2836,"avg_fare":18.6353},"Staten Island":{"rides":371,"avg_fare":18.5801}},"avg_fare":27.7331,"avg_pay":23.0789,"avg_miles":4.8499,"avg_trip_time":1565.2589},{"h":17,"rides":26302,"boroughs":{"Manhattan":{"rides":9753,"avg_fare":36.1148},"Brooklyn":{"rides":7547,"avg_fare":20.0612},"Queens":{"rides":5471,"avg_fare":30.255},"Bronx":{"rides":3113,"avg_fare":18.1508},"Staten Island":{"rides":418,"avg_fare":19.9846}},"avg_fare":27.9071,"avg_pay":22.4616,"avg_miles":4.4313,"avg_trip_time":1409.1049},{"h":18,"rides":28130,"boroughs":{"Manhattan":{"rides":11920,"avg_fare":34.0621},"Brooklyn":{"rides":6887,"avg_fare":20.2023},"Queens":{"rides":5839,"avg_fare":27.4617},"Bronx":{"rides":3185,"avg_fare":16.6928},"Staten Island":{"rides":297,"avg_fare":19.2375}},"avg_fare":27.1739,"avg_pay":22.1965,"avg_miles":4.1751,"avg_trip_time":1210.7164},{"h":19,"rides":22515,"boroughs":{"Manhattan":{"rides":10252,"avg_fare":27.8212},"Brooklyn":{"rides":5331,"avg_fare":18.2744},"Queens":{"rides":4399,"avg_fare":27.9338},"Bronx":{"rides":2287,"avg_fare":16.2146},"Staten Island":{"rides":246,"avg_fare":17.6748}},"avg_fare":24.2929,"avg_pay":19.206,"avg_miles":4.7073,"avg_trip_time":1121.8145},{"h":20,"rides":20408,"boroughs":{"Manhattan":{"rides":9806,"avg_fare":29.8009},"Brooklyn":{"rides":4418,"avg_fare":18.2694},"Queens":{"rides":3992,"avg_fare":28.8642},"Bronx":{"rides":1988,"avg_fare":16.0288},"Staten Island":{"rides":204,"avg_fare":20.3543}},"avg_fare":25.6853,"avg_pay":19.7544,"avg_miles":5.3445,"avg_trip_time":1118.2034},{"h":21,"rides":19580,"boroughs":{"Manhattan":{"rides":9955,"avg_fare":30.8235},"Brooklyn":{"rides":4068,"avg_fare":18.7972},"Queens":{"rides":3723,"avg_fare":32.4892},"Bronx":{"rides":1679,"avg_fare":15.4046},"Staten Island":{"rides":154,"avg_fare":19.4234}},"avg_fare":27.229,"avg_pay":20.4418,"avg_miles":5.8379,"avg_trip_time":1106.1747},{"h":22,"rides":17692,"boroughs":{"Manhattan":{"rides":8860,"avg_fare":27.4682},"Brooklyn":{"rides":3764,"avg_fare":17.8906},"Queens":{"rides":3352,"avg_fare":33.5754},"Bronx":{"rides":1572,"avg_fare":16.7078},"Staten Island":{"rides":144,"avg_fare":18.9776}},"avg_fare":25.5624,"avg_pay":19.8375,"avg_miles":5.8114,"avg_trip_time":1078.3829},{"h":23,"rides":14300,"boroughs":{"Manhattan":{"rides":6435,"avg_fare":26.1563},"Brooklyn":{"rides":3106,"avg_fare":17.5273},"Queens":{"rides":3061,"avg_fare":33.0419},"Bronx":{"rides":1582,"avg_fare":15.6918},"Staten Island":{"rides":116,"avg_fare":15.7345}},"avg_fare":24.5137,"avg_pay":19.6375,"avg_miles":5.8303,"avg_trip_time":1061.8614}]}