{"date":"2023-01-23","hours":[{"h":0,"rides":10557,"boroughs":{"Manhattan":{"rides":3636,"avg_fare":18.7816},"Brooklyn":{"rides":2728,"avg_fare":15.8274},"Queens":{"rides":2673,"avg_fare":18.4367},"Bronx":{"rides":1437,"avg_fare":14.3309},"Staten Island":{"rides":83,"avg_fare":20.5816}},"avg_fare":17.5916,"avg_pay":15.4999,"avg_miles":5.246},{"h":1,"rides":5910,"boroughs":{"Manhattan":{"rides":2051,"avg_fare":19.1965},"Brooklyn":{"rides":1503,"avg_fare":15.8193},"Queens":{"rides":1509,"avg_fare":17.4541},"Bronx":{"rides":794,"avg_fare":14.6493},"Staten Island":{"rides":53,"avg_fare":17.2615}},"avg_fare":16.8761,"avg_pay":14.6372,"avg_miles":5.048},{"h":2,"rides":3642,"boroughs":{"Manhattan":{"rides":1269,"avg_fare":19.8453},"Brooklyn":{"rides":924,"avg_fare":16.6635},"Queens":{"rides":905,"avg_fare":18.7617},"Bronx":{"rides":508,"avg_fare":16.6714},"Staten Island":{"rides":36,"avg_fare":24.167}},"avg_fare":19.2218,"avg_pay":16.4575,"avg_miles":5.8755},{"h":3,"rides":3210,"boroughs":{"Manhattan":{"rides":1040,"avg_fare":24.7821},"Brooklyn":{"rides":784,"avg_fare":21.2079},"Queens":{"rides":852,"avg_fare":20.9025},"Bronx":{"rides":493,"avg_fare":17.1232},"Staten Island":{"rides":39,"avg_fare":22.1779}},"avg_fare":19.9256,"avg_pay":16.0193,"avg_miles":6.0369},{"h":4,"rides":4578,"boroughs":{"Manhattan":{"rides":1424,"avg_fare":31.6858},"Brooklyn":{"rides":1173,"avg_fare":27.6625},"Queens":{"rides":1244,"avg_fare":21.57},"Bronx":{"rides":687,"avg_fare":19.6278},"Staten Island":{"rides":50,"avg_fare":32.2453}},"avg_fare":26.5583,"avg_pay":21.1111,"avg_miles":8.1569},{"h":5,"rides":7253,"boroughs":{"Manhattan":{"rides":2359,"avg_fare":31.4553},"Brooklyn":{"rides":1802,"avg_fare":28.896},"Queens":{"rides":1819,"avg_fare":22.3489},"Bronx":{"rides":1147,"avg_fare":18.9454},"Staten Island":{"rides":126,"avg_fare":24.4531}},"avg_fare":25.2197,"avg_pay":20.4972,"avg_miles":7.3619},{"h":6,"rides":13212,"boroughs":{"Manhattan":{"rides":4478,"avg_fare":25.5601},"Brooklyn":{"rides":3125,"avg_fare":26.38},"Queens":{"rides":3286,"avg_fare":22.5064},"Bronx":{"rides":2107,"avg_fare":20.3997},"Staten Island":{"rides":215,"avg_fare":27.0432}},"avg_fare":22.1032,"avg_pay":17.6818,"avg_miles":5.628},{"h":7,"rides":21725,"boroughs":{"Manhattan":{"rides":7616,"avg_fare":24.6222},"Brooklyn":{"rides":5085,"avg_fare":25.3042},"Queens":{"rides":4934,"avg_fare":23.6109},"Bronx":{"rides":3719,"avg_fare":20.4054},"Staten Island":{"rides":370,"avg_fare":20.2078}},"avg_fare":24.8268,"avg_pay":19.4259,"avg_miles":5.0098},{"h":8,"rides":28468,"boroughs":{"Manhattan":{"rides":10541,"avg_fare":22.5528},"Brooklyn":{"rides":6627,"avg_fare":21.1345},"Queens":{"rides":6183,"avg_fare":20.3987},"Bronx":{"rides":4641,"avg_fare":17.6284},"Staten Island":{"rides":475,"avg_fare":18.5382}},"avg_fare":19.0771,"avg_pay":15.3364,"avg_miles":4.1191},{"h":9,"rides":23023,"boroughs":{"Manhattan":{"rides":9140,"avg_fare":20.6011},"Brooklyn":{"rides":5845,"avg_fare":18.9185},"Queens":{"rides":4675,"avg_fare":20.068},"Bronx":{"rides":3039,"avg_fare":16.5886},"Staten Island":{"rides":322,"avg_fare":18.7898}},"avg_fare":18.196,"avg_pay":15.9297,"avg_miles":4.2311},{"h":10,"rides":19881,"boroughs":{"Manhattan":{"rides":8140,"avg_fare":20.1487},"Brooklyn":{"rides":5014,"avg_fare":19.3666},"Queens":{"rides":4066,"avg_fare":19.7588},"Bronx":{"rides":2390,"avg_fare":17.7677},"Staten Island":{"rides":271,"avg_fare":19.5263}},"avg_fare":19.3136,"avg_pay":16.0329,"avg_miles":4.7966},{"h":11,"rides":18658,"boroughs":{"Manhattan":{"rides":7915,"avg_fare":21.009},"Brooklyn":{"rides":4607,"avg_fare":18.6029},"Queens":{"rides":3664,"avg_fare":19.671},"Bronx":{"rides":2181,"avg_fare":16.4111},"Staten Island":{"rides":290,"avg_fare":19.1771}},"avg_fare":20.7418,"avg_pay":17.1731,"avg_miles":5.8532},{"h":12,"rides":18113,"boroughs":{"Manhattan":{"rides":7904,"avg_fare":20.7737},"Brooklyn":{"rides":4408,"avg_fare":18.6594},"Queens":{"rides":3440,"avg_fare":18.8953},"Bronx":{"rides":2083,"avg_fare":15.8706},"Staten Island":{"rides":277,"avg_fare":17.0968}},"avg_fare":19.3826,"avg_pay":15.7251,"avg_miles":5.1332},{"h":13,"rides":19782,"boroughs":{"Manhattan":{"rides":8302,"avg_fare":21.6794},"Brooklyn":{"rides":4818,"avg_fare":18.1631},"Queens":{"rides":3952,"avg_fare":18.5894},"Bronx":{"rides":2401,"avg_fare":15.8071},"Staten Island":{"rides":309,"avg_fare":16.7567}},"avg_fare":18.1991,"avg_pay":15.1888,"avg_miles":4.4031},{"h":14,"rides":22726,"boroughs":{"Manhattan":{"rides":8830,"avg_fare":21.785},"Brooklyn":{"rides":5677,"avg_fare":18.0589},"Queens":{"rides":4857,"avg_fare":18.2015},"Bronx":{"rides":2968,"avg_fare":15.8957},"Staten Island":{"rides":394,"avg_fare":19.3768}},"avg_fare":18.6636,"avg_pay":15.5814,"avg_miles":4.3263},{"h":15,"rides":24162,"boroughs":{"Manhattan":{"rides":9474,"avg_fare":22.0583},"Brooklyn":{"rides":5948,"avg_fare":18.279},"Queens":{"rides":5107,"avg_fare":18.089},"Bronx":{"rides":3264,"avg_fare":16.3298},"Staten Island":{"rides":367,"avg_fare":18.3055}},"avg_fare":18.5228,"avg_pay":15.3362,"avg_miles":3.9776},{"h":16,"rides":21933,"boroughs":{"Manhattan":{"rides":8569,"avg_fare":22.4466},"Brooklyn":{"rides":5512,"avg_fare":18.8923},"Queens":{"rides":4482,"avg_fare":18.9373},"Bronx":{"rides":3062,"avg_fare":16.8156},"Staten Island":{"rides":308,"avg_fare":18.4434}},"avg_fare":19.1071,"avg_pay":15.9095,"avg_miles":4.3719},{"h":17,"rides":25575,"boroughs":{"Manhattan":{"rides":11013,"avg_fare":20.7284},"Brooklyn":{"rides":6165,"avg_fare":17.6514},"Queens":{"rides":4871,"avg_fare":18.4495},"Bronx":{"rides":3184,"avg_fare":15.7689},"Staten Island":{"rides":341,"avg_fare":17.1692}},"avg_fare":17.3479,"avg_pay":14.3868,"avg_miles":3.8726},{"h":18,"rides":25847,"boroughs":{"Manhattan":{"rides":12179,"avg_fare":18.6781},"Brooklyn":{"rides":6045,"avg_fare":15.6533},"Queens":{"rides":4575,"avg_fare":17.0736},"Bronx":{"rides":2778,"avg_fare":14.7728},"Staten Island":{"rides":269,"avg_fare":16.0686}},"avg_fare":15.2511,"avg_pay":13.2088,"avg_miles":3.745},{"h":19,"rides":23097,"boroughs":{"Manhattan":{"rides":10997,"avg_fare":18.9508},"Brooklyn":{"rides":5451,"avg_fare":15.3524},"Queens":{"rides":4189,"avg_fare":16.9788},"Bronx":{"rides":2219,"avg_fare":14.9155},"Staten Island":{"rides":241,"avg_fare":17.1397}},"avg_fare":16.6674,"avg_pay":14.5192,"avg_miles":4.6711},{"h":20,"rides":20459,"boroughs":{"Manhattan":{"rides":10286,"avg_fare":19.9659},"Brooklyn":{"rides":4601,"avg_fare":15.5369},"Queens":{"rides":3547,"avg_fare":17.421},"Bronx":{"rides":1847,"avg_fare":14.7641},"Staten Island":{"rides":177,"avg_fare":16.2627}},"avg_fare":13.9434,"avg_pay":12.009,"avg_miles":3.9347},{"h":21,"rides":19611,"boroughs":{"Manhattan":{"rides":10232,"avg_fare":20.2042},"Brooklyn":{"rides":4052,"avg_fare":15.6641},"Queens":{"rides":3359,"avg_fare":17.2486},"Bronx":{"rides":1820,"avg_fare":14.916},"Staten Island":{"rides":148,"avg_fare":16.6506}},"avg_fare":16.9367,"avg_pay":14.5258,"avg_miles":4.8676},{"h":22,"rides":17430,"boroughs":{"Manhattan":{"rides":8448,"avg_fare":19.8439},"Brooklyn":{"rides":3857,"avg_fare":15.505},"Queens":{"rides":3331,"avg_fare":18.1392},"Bronx":{"rides":1649,"avg_fare":14.0952},"Staten Island":{"rides":144,"avg_fare":14.9719}},"avg_fare":16.4359,"avg_pay":14.133,"avg_miles":4.8538},{"h":23,"rides":12936,"boroughs":{"Manhattan":{"rides":5283,"avg_fare":19.3348},"Brooklyn":{"rides":3116,"avg_fare":15.7124},"Queens":{"rides":2818,"avg_fare":17.3872},"Bronx":{"rides":1605,"avg_fare":14.4731},"Staten Island":{"rides":113,"avg_fare":15.4851}},"avg_fare":15.7938,"avg_pay":13.399,"avg_miles":3.9784}]}