{"date":"2024-04-04","hours":[{"h":0,"rides":12948,"boroughs":{"Manhattan":{"rides":5692,"avg_fare":24.6213},"Brooklyn":{"rides":2937,"avg_fare":18.0269},"Queens":{"rides":2903,"avg_fare":21.3152},"Bronx":{"rides":1307,"avg_fare":15.6276},"Staten Island":{"rides":109,"avg_fare":17.2105}},"avg_fare":19.3603,"avg_pay":15.4005,"avg_miles":4.6423},{"h":1,"rides":7979,"boroughs":{"Manhattan":{"rides":3506,"avg_fare":24.1906},"Brooklyn":{"rides":1721,"avg_fare":18.1719},"Queens":{"rides":1940,"avg_fare":20.3375},"Bronx":{"rides":742,"avg_fare":15.7173},"Staten Island":{"rides":70,"avg_fare":21.298}},"avg_fare":19.9431,"avg_pay":15.9932,"avg_miles":4.8939},{"h":2,"rides":5252,"boroughs":{"Manhattan":{"rides":2071,"avg_fare":24.5571},"Brooklyn":{"rides":1126,"avg_fare":19.0793},"Queens":{"rides":1480,"avg_fare":20.5919},"Bronx":{"rides":544,"avg_fare":17.0686},"Staten Island":{"rides":30,"avg_fare":20.7092}},"avg_fare":20.4293,"avg_pay":16.6121,"avg_miles":5.2496},{"h":3,"rides":4265,"boroughs":{"Manhattan":{"rides":1586,"avg_fare":31.0516},"Brooklyn":{"rides":1028,"avg_fare":23.6099},"Queens":{"rides":1107,"avg_fare":23.171},"Bronx":{"rides":500,"avg_fare":21.7655},"Staten Island":{"rides":44,"avg_fare":26.7346}},"avg_fare":25.2665,"avg_pay":20.0878,"avg_miles":6.7388},{"h":4,"rides":5521,"boroughs":{"Manhattan":{"rides":1874,"avg_fare":43.589},"Brooklyn":{"rides":1367,"avg_fare":30.075},"Queens":{"rides":1466,"avg_fare":24.6539},"Bronx":{"rides":731,"avg_fare":22.0438},"Staten Island":{"rides":82,"avg_fare":43.8652}},"avg_fare":33.3311,"avg_pay":25.8137,"avg_miles":8.8535},{"h":5,"rides":8645,"boroughs":{"Manhattan":{"rides":2575,"avg_fare":43.9827},"Brooklyn":{"rides":2265,"avg_fare":31.8636},"Queens":{"rides":2325,"avg_fare":24.1785},"Bronx":{"rides":1320,"avg_fare":23.2044},"Staten Island":{"rides":158,"avg_fare":30.204}},"avg_fare":29.7397,"avg_pay":23.1895,"avg_miles":6.4201},{"h":6,"rides":15542,"boroughs":{"Manhattan":{"rides":4845,"avg_fare":33.9806},"Brooklyn":{"rides":4063,"avg_fare":27.2006},"Queens":{"rides":3645,"avg_fare":24.5609},"Bronx":{"rides":2688,"avg_fare":23.3787},"Staten Island":{"rides":301,"avg_fare":23.555}},"avg_fare":26.5352,"avg_pay":20.6957,"avg_miles":6.0135},{"h":7,"rides":25031,"boroughs":{"Manhattan":{"rides":7723,"avg_fare":29.6201},"Brooklyn":{"rides":6594,"avg_fare":26.1262},"Queens":{"rides":5835,"avg_fare":24.2836},"Bronx":{"rides":4375,"avg_fare":24.2149},"Staten Island":{"rides":501,"avg_fare":24.4442}},"avg_fare":27.2815,"avg_pay":21.3037,"avg_miles":5.2368},{"h":8,"rides":31408,"boroughs":{"Manhattan":{"rides":10617,"avg_fare":29.0418},"Brooklyn":{"rides":7940,"avg_fare":23.6157},"Queens":{"rides":6804,"avg_fare":21.9795},"Bronx":{"rides":5446,"avg_fare":19.99},"Staten Island":{"rides":601,"avg_fare":21.7402}},"avg_fare":23.2735,"avg_pay":18.7807,"avg_miles":4.2987},{"h":9,"rides":28002,"boroughs":{"Manhattan":{"rides":10691,"avg_fare":27.5119},"Brooklyn":{"rides":7072,"avg_fare":22.993},"Queens":{"rides":5856,"avg_fare":22.0951},"Bronx":{"rides":3934,"avg_fare":18.7685},"Staten Island":{"rides":448,"avg_fare":21.8545}},"avg_fare":23.1588,"avg_pay":19.0677,"avg_miles":4.5947},{"h":10,"rides":23221,"boroughs":{"Manhattan":{"rides":9009,"avg_fare":27.9695},"Brooklyn":{"rides":5730,"avg_fare":22.7297},"Queens":{"rides":4919,"avg_fare":23.3217},"Bronx":{"rides":3189,"avg_fare":18.7564},"Staten Island":{"rides":374,"avg_fare":20.8685}},"avg_fare":22.7292,"avg_pay":18.1821,"avg_miles":4.6505},{"h":11,"rides":21730,"boroughs":{"Manhattan":{"rides":8759,"avg_fare":29.4636},"Brooklyn":{"rides":5269,"avg_fare":22.3991},"Queens":{"rides":4591,"avg_fare":24.1347},"Bronx":{"rides":2791,"avg_fare":19.0234},"Staten Island":{"rides":320,"avg_fare":22.6996}},"avg_fare":23.5441,"avg_pay":18.6752,"avg_miles":4.7947},{"h":12,"rides":21385,"boroughs":{"Manhattan":{"rides":8723,"avg_fare":29.9254},"Brooklyn":{"rides":5229,"avg_fare":22.1437},"Queens":{"rides":4371,"avg_fare":22.7334},"Bronx":{"rides":2731,"avg_fare":19.0127},"Staten Island":{"rides":331,"avg_fare":22.1725}},"avg_fare":23.1975,"avg_pay":18.3367,"avg_miles":4.699},{"h":13,"rides":22795,"boroughs":{"Manhattan":{"rides":9184,"avg_fare":31.6535},"Brooklyn":{"rides":5608,"avg_fare":22.9485},"Queens":{"rides":4705,"avg_fare":22.7357},"Bronx":{"rides":2924,"avg_fare":19.554},"Staten Island":{"rides":373,"avg_fare":23.3869}},"avg_fare":22.2764,"avg_pay":17.5361,"avg_miles":4.3679},{"h":14,"rides":25123,"boroughs":{"Manhattan":{"rides":9471,"avg_fare":32.0447},"Brooklyn":{"rides":6297,"avg_fare":22.5561},"Queens":{"rides":5358,"avg_fare":22.6213},"Bronx":{"rides":3513,"avg_fare":19.7617},"Staten Island":{"rides":483,"avg_fare":21.7343}},"avg_fare":23.6747,"avg_pay":20.0124,"avg_miles":4.558},{"h":15,"rides":25716,"boroughs":{"Manhattan":{"rides":9978,"avg_fare":32.9102},"Brooklyn":{"rides":6305,"avg_fare":22.7948},"Queens":{"rides":5388,"avg_fare":23.5724},"Bronx":{"rides":3566,"avg_fare":20.981},"Staten Island":{"rides":478,"avg_fare":20.9598}},"avg_fare":22.8947,"avg_pay":17.7878,"avg_miles":4.1147},{"h":16,"rides":26053,"boroughs":{"Manhattan":{"rides":10317,"avg_fare":33.4591},"Brooklyn":{"rides":6560,"avg_fare":23.4713},"Queens":{"rides":5153,"avg_fare":23.3807},"Bronx":{"rides":3563,"avg_fare":20.0256},"Staten Island":{"rides":460,"avg_fare":23.1416}},"avg_fare":24.6957,"avg_pay":19.3773,"avg_miles":4.4308},{"h":17,"rides":30075,"boroughs":{"Manhattan":{"rides":12352,"avg_fare":30.4308},"Brooklyn":{"rides":7588,"avg_fare":22.0105},"Queens":{"rides":5716,"avg_fare":23.069},"Bronx":{"rides":3935,"avg_fare":18.7315},"Staten Island":{"rides":484,"avg_fare":20.559}},"avg_fare":22.9602,"avg_pay":18.2232,"avg_miles":4.176},{"h":18,"rides":31012,"boroughs":{"Manhattan":{"rides":13948,"avg_fare":27.368},"Brooklyn":{"rides":7640,"avg_fare":20.5128},"Queens":{"rides":5522,"avg_fare":21.257},"Bronx":{"rides":3521,"avg_fare":18.6335},"Staten Island":{"rides":381,"avg_fare":20.3846}},"avg_fare":21.6312,"avg_pay":17.4821,"avg_miles":4.2876},{"h":19,"rides":30812,"boroughs":{"Manhattan":{"rides":13546,"avg_fare":25.8959},"Brooklyn":{"rides":8040,"avg_fare":19.0331},"Queens":{"rides":5562,"avg_fare":21.2388},"Bronx":{"rides":3309,"avg_fare":18.4991},"Staten Island":{"rides":355,"avg_fare":20.2779}},"avg_fare":20.989,"avg_pay":17.4813,"avg_miles":4.5784},{"h":20,"rides":30192,"boroughs":{"Manhattan":{"rides":12833,"avg_fare":29.2909},"Brooklyn":{"rides":8824,"avg_fare":18.09},"Queens":{"rides":5053,"avg_fare":20.9209},"Bronx":{"rides":3141,"avg_fare":16.9453},"Staten Island":{"rides":341,"avg_fare":18.3603}},"avg_fare":20.7215,"avg_pay":16.9574,"avg_miles":4.6085},{"h":21,"rides":26704,"boroughs":{"Manhattan":{"rides":11858,"avg_fare":32.7744},"Brooklyn":{"rides":7196,"avg_fare":18.5232},"Queens":{"rides":4583,"avg_fare":19.4838},"Bronx":{"rides":2789,"avg_fare":17.2567},"Staten Island":{"rides":278,"avg_fare":25.0685}},"avg_fare":22.6213,"avg_pay":18.1811,"avg_miles":5.226},{"h":22,"rides":25727,"boroughs":{"Manhattan":{"rides":11183,"avg_fare":35.1981},"Brooklyn":{"rides":7106,"avg_fare":18.9334},"Queens":{"rides":4700,"avg_fare":20.5097},"Bronx":{"rides":2500,"avg_fare":17.0302},"Staten Island":{"rides":236,"avg_fare":21.3027}},"avg_fare":20.4548,"avg_pay":16.2903,"avg_miles":4.6128},{"h":23,"rides":23477,"boroughs":{"Manhattan":{"rides":10594,"avg_fare":28.1671},"Brooklyn":{"rides":6126,"avg_fare":18.8839},"Queens":{"rides":4260,"avg_fare":20.9394},"Bronx":{"rides":2311,"avg_fare":16.4398},"Staten Island":{"rides":186,"avg_fare":17.672}},"avg_fare":20.4204,"avg_pay":16.8025,"avg_miles":4.9134}]}