{"date":"2024-12-08","hours":[{"h":0,"rides":34573,"boroughs":{"Manhattan":{"rides":15150,"avg_fare":38.8947},"Brooklyn":{"rides":10347,"avg_fare":25.4477},"Queens":{"rides":5488,"avg_fare":22.3246},"Bronx":{"rides":3244,"avg_fare":18.6775},"Staten Island":{"rides":342,"avg_fare":26.1999}},"avg_fare":27.2741,"avg_pay":21.9763,"avg_miles":6.3799},{"h":1,"rides":28633,"boroughs":{"Manhattan":{"rides":13173,"avg_fare":31.7521},"Brooklyn":{"rides":8501,"avg_fare":21.6478},"Queens":{"rides":4201,"avg_fare":22.1622},"Bronx":{"rides":2439,"avg_fare":18.0001},"Staten Island":{"rides":317,"avg_fare":21.8579}},"avg_fare":21.76,"avg_pay":19.0238,"avg_miles":5.3398},{"h":2,"rides":22376,"boroughs":{"Manhattan":{"rides":10584,"avg_fare":26.4428},"Brooklyn":{"rides":6448,"avg_fare":21.4238},"Queens":{"rides":3310,"avg_fare":21.3802},"Bronx":{"rides":1850,"avg_fare":18.172},"Staten Island":{"rides":182,"avg_fare":23.8776}},"avg_fare":24.3602,"avg_pay":20.8299,"avg_miles":6.1276},{"h":3,"rides":16474,"boroughs":{"Manhattan":{"rides":7555,"avg_fare":27.7634},"Brooklyn":{"rides":4551,"avg_fare":23.3087},"Queens":{"rides":2833,"avg_fare":24.2774},"Bronx":{"rides":1398,"avg_fare":19.3049},"Staten Island":{"rides":136,"avg_fare":26.7216}},"avg_fare":21.7527,"avg_pay":19.0495,"avg_miles":5.388},{"h":4,"rides":12854,"boroughs":{"Manhattan":{"rides":5052,"avg_fare":33.3849},"Brooklyn":{"rides":3275,"avg_fare":27.0354},"Queens":{"rides":3064,"avg_fare":25.543},"Bronx":{"rides":1332,"avg_fare":20.4773},"Staten Island":{"rides":130,"avg_fare":28.2109}},"avg_fare":26.7669,"avg_pay":23.0927,"avg_miles":7.3305},{"h":5,"rides":9522,"boroughs":{"Manhattan":{"rides":3076,"avg_fare":37.777},"Brooklyn":{"rides":2485,"avg_fare":29.6677},"Queens":{"rides":2533,"avg_fare":25.3835},"Bronx":{"rides":1300,"avg_fare":20.4896},"Staten Island":{"rides":128,"avg_fare":30.5649}},"avg_fare":28.7765,"avg_pay":24.4611,"avg_miles":7.4853},{"h":6,"rides":11387,"boroughs":{"Manhattan":{"rides":3645,"avg_fare":34.2443},"Brooklyn":{"rides":2830,"avg_fare":27.9368},"Queens":{"rides":2862,"avg_fare":23.5081},"Bronx":{"rides":1785,"avg_fare":20.6725},"Staten Island":{"rides":265,"avg_fare":23.1123}},"avg_fare":25.8948,"avg_pay":23.278,"avg_miles":6.993},{"h":7,"rides":13597,"boroughs":{"Manhattan":{"rides":4430,"avg_fare":32.5279},"Brooklyn":{"rides":3576,"avg_fare":24.7826},"Queens":{"rides":3228,"avg_fare":22.274},"Bronx":{"rides":2118,"avg_fare":20.008},"Staten Island":{"rides":244,"avg_fare":26.3801}},"avg_fare":27.7121,"avg_pay":26.6504,"avg_miles":8.7403},{"h":8,"rides":16022,"boroughs":{"Manhattan":{"rides":5732,"avg_fare":29.5517},"Brooklyn":{"rides":4354,"avg_fare":21.9857},"Queens":{"rides":3596,"avg_fare":22.4031},"Bronx":{"rides":2118,"avg_fare":18.3315},"Staten Island":{"rides":222,"avg_fare":20.8795}},"avg_fare":22.6303,"avg_pay":19.7162,"avg_miles":6.0332},{"h":9,"rides":20575,"boroughs":{"Manhattan":{"rides":7575,"avg_fare":26.1583},"Brooklyn":{"rides":5483,"avg_fare":21.0512},"Queens":{"rides":4622,"avg_fare":20.9934},"Bronx":{"rides":2572,"avg_fare":18.0462},"Staten Island":{"rides":323,"avg_fare":20.7785}},"avg_fare":21.4055,"avg_pay":18.0024,"avg_miles":5.4604},{"h":10,"rides":25034,"boroughs":{"Manhattan":{"rides":9575,"avg_fare":26.475},"Brooklyn":{"rides":6656,"avg_fare":20.4057},"Queens":{"rides":5565,"avg_fare":21.4578},"Bronx":{"rides":2895,"avg_fare":17.7977},"Staten Island":{"rides":342,"avg_fare":21.9076}},"avg_fare":19.6223,"avg_pay":16.2926,"avg_miles":4.488},{"h":11,"rides":26163,"boroughs":{"Manhattan":{"rides":10583,"avg_fare":28.1379},"Brooklyn":{"rides":6872,"avg_fare":20.5879},"Queens":{"rides":5424,"avg_fare":23.345},"Bronx":{"rides":2911,"avg_fare":18.7087},"Staten Island":{"rides":372,"avg_fare":23.5779}},"avg_fare":21.5896,"avg_pay":18.258,"avg_miles":5.0396},{"h":12,"rides":25793,"boroughs":{"Manhattan":{"rides":10472,"avg_fare":30.727},"Brooklyn":{"rides":6777,"avg_fare":22.1133},"Queens":{"rides":5352,"avg_fare":21.7093},"Bronx":{"rides":2837,"avg_fare":18.4914},"Staten Island":{"rides":355,"avg_fare":21.1178}},"avg_fare":22.8318,"avg_pay":18.9866,"avg_miles":5.1232},{"h":13,"rides":25884,"boroughs":{"Manhattan":{"rides":10058,"avg_fare":32.0152},"Brooklyn":{"rides":7075,"avg_fare":22.4736},"Queens":{"rides":5318,"avg_fare":22.2477},"Bronx":{"rides":3061,"avg_fare":19.1016},"Staten Island":{"rides":370,"avg_fare":22.0478}},"avg_fare":22.2951,"avg_pay":19.385,"avg_miles":4.9467},{"h":14,"rides":26701,"boroughs":{"Manhattan":{"rides":9793,"avg_fare":35.0956},"Brooklyn":{"rides":7418,"avg_fare":23.0303},"Queens":{"rides":5816,"avg_fare":22.0103},"Bronx":{"rides":3304,"avg_fare":18.4692},"Staten Island":{"rides":369,"avg_fare":22.7133}},"avg_fare":21.7165,"avg_pay":18.1115,"avg_miles":4.6234},{"h":15,"rides":26669,"boroughs":{"Manhattan":{"rides":9417,"avg_fare":36.4873},"Brooklyn":{"rides":7541,"avg_fare":21.8056},"Queens":{"rides":5943,"avg_fare":23.2231},"Bronx":{"rides":3406,"avg_fare":19.6009},"Staten Island":{"rides":362,"avg_fare":21.3546}},"avg_fare":24.4943,"avg_pay":20.4006,"avg_miles":5.194},{"h":16,"rides":26559,"boroughs":{"Manhattan":{"rides":9123,"avg_fare":39.775},"Brooklyn":{"rides":7747,"avg_fare":22.7484},"Queens":{"rides":6082,"avg_fare":24.2936},"Bronx":{"rides":3256,"avg_fare":18.2399},"Staten Island":{"rides":351,"avg_fare":25.2936}},"avg_fare":26.0701,"avg_pay":21.6112,"avg_miles":5.4763},{"h":17,"rides":27773,"boroughs":{"Manhattan":{"rides":9759,"avg_fare":36.7446},"Brooklyn":{"rides":7995,"avg_fare":21.2286},"Queens":{"rides":6090,"avg_fare":22.2981},"Bronx":{"rides":3545,"avg_fare":19.7754},"Staten Island":{"rides":384,"avg_fare":25.955}},"avg_fare":25.2003,"avg_pay":21.3797,"avg_miles":5.4895},{"h":18,"rides":28054,"boroughs":{"Manhattan":{"rides":10041,"avg_fare":31.1844},"Brooklyn":{"rides":8185,"avg_fare":21.8616},"Queens":{"rides":6095,"avg_fare":23.2915},"Bronx":{"rides":3343,"avg_fare":18.2445},"Staten Island":{"rides":389,"avg_fare":24.38}},"avg_fare":27.6703,"avg_pay":30.2226,"avg_miles":8.6777},{"h":19,"rides":27163,"boroughs":{"Manhattan":{"rides":10373,"avg_fare":27.1896},"Brooklyn":{"rides":7789,"avg_fare":21.3701},"Queens":{"rides":5654,"avg_fare":22.0805},"Bronx":{"rides":3041,"avg_fare":18.7982},"Staten Island":{"rides":305,"avg_fare":25.3979}},"avg_fare":27.6644,"avg_pay":23.1856,"avg_miles":7.0699},{"h":20,"rides":25379,"boroughs":{"Manhattan":{"rides":9551,"avg_fare":25.688},"Brooklyn":{"rides":6989,"avg_fare":20.0914},"Queens":{"rides":5703,"avg_fare":22.674},"Bronx":{"rides":2839,"avg_fare":17.5632},"Staten Island":{"rides":297,"avg_fare":22.8149}},"avg_fare":21.7663,"avg_pay":19.8844,"avg_miles":5.6293},{"h":21,"rides":23654,"boroughs":{"Manhattan":{"rides":9259,"avg_fare":24.377},"Brooklyn":{"rides":6270,"avg_fare":19.4831},"Queens":{"rides":5170,"avg_fare":22.1928},"Bronx":{"rides":2702,"avg_fare":18.0489},"Staten Island":{"rides":252,"avg_fare":20.0756}},"avg_fare":18.9946,"avg_pay":16.9131,"avg_miles":4.7805},{"h":22,"rides":22581,"boroughs":{"Manhattan":{"rides":8252,"avg_fare":23.6749},"Brooklyn":{"rides":6274,"avg_fare":19.5681},"Queens":{"rides":5079,"avg_fare":21.1163},"Bronx":{"rides":2741,"avg_fare":18.2259},"Staten Island":{"rides":234,"avg_fare":20.172}},"avg_fare":18.4695,"avg_pay":16.7629,"avg_miles":4.7544},{"h":23,"rides":18615,"boroughs":{"Manhattan":{"rides":6166,"avg_fare":22.4221},"Brooklyn":{"rides":4931,"avg_fare":18.9093},"Queens":{"rides":4888,"avg_fare":21.4193},"Bronx":{"rides":2412,"avg_fare":16.3025},"Staten Island":{"rides":217,"avg_fare":21.459}},"avg_fare":22.447,"avg_pay":19.3884,"avg_miles":6.7936}]}