{"date":"2024-08-10","hours":[{"h":0,"rides":23357,"boroughs":{"Manhattan":{"rides":10184,"avg_fare":23.3799},"Brooklyn":{"rides":6508,"avg_fare":20.2872},"Queens":{"rides":4189,"avg_fare":21.0882},"Bronx":{"rides":2220,"avg_fare":17.5383},"Staten Island":{"rides":256,"avg_fare":20.7739}},"avg_fare":20.6135,"avg_pay":17.716,"avg_miles":5.1085},{"h":1,"rides":17760,"boroughs":{"Manhattan":{"rides":8110,"avg_fare":23.9},"Brooklyn":{"rides":4958,"avg_fare":20.013},"Queens":{"rides":2935,"avg_fare":20.4457},"Bronx":{"rides":1612,"avg_fare":17.6195},"Staten Island":{"rides":145,"avg_fare":24.2828}},"avg_fare":21.2522,"avg_pay":18.049,"avg_miles":5.3745},{"h":2,"rides":13596,"boroughs":{"Manhattan":{"rides":6377,"avg_fare":22.8698},"Brooklyn":{"rides":3901,"avg_fare":20.0559},"Queens":{"rides":2096,"avg_fare":21.4024},"Bronx":{"rides":1086,"avg_fare":18.9689},"Staten Island":{"rides":136,"avg_fare":26.4883}},"avg_fare":21.9571,"avg_pay":18.266,"avg_miles":5.6209},{"h":3,"rides":10444,"boroughs":{"Manhattan":{"rides":4502,"avg_fare":28.6781},"Brooklyn":{"rides":2977,"avg_fare":23.2497},"Queens":{"rides":1867,"avg_fare":24.091},"Bronx":{"rides":997,"avg_fare":19.839},"Staten Island":{"rides":101,"avg_fare":30.7007}},"avg_fare":25.3117,"avg_pay":20.5096,"avg_miles":6.6486},{"h":4,"rides":8242,"boroughs":{"Manhattan":{"rides":2978,"avg_fare":36.0569},"Brooklyn":{"rides":2263,"avg_fare":26.9822},"Queens":{"rides":1949,"avg_fare":24.5435},"Bronx":{"rides":957,"avg_fare":24.591},"Staten Island":{"rides":94,"avg_fare":31.8742}},"avg_fare":27.2313,"avg_pay":22.0198,"avg_miles":7.0291},{"h":5,"rides":7478,"boroughs":{"Manhattan":{"rides":2293,"avg_fare":37.9483},"Brooklyn":{"rides":1953,"avg_fare":30.7372},"Queens":{"rides":1982,"avg_fare":24.8818},"Bronx":{"rides":1115,"avg_fare":22.566},"Staten Island":{"rides":134,"avg_fare":36.6898}},"avg_fare":29.0555,"avg_pay":22.6698,"avg_miles":7.495},{"h":6,"rides":10289,"boroughs":{"Manhattan":{"rides":3024,"avg_fare":35.2057},"Brooklyn":{"rides":2651,"avg_fare":27.7474},"Queens":{"rides":2645,"avg_fare":25.3729},"Bronx":{"rides":1788,"avg_fare":24.4985},"Staten Island":{"rides":181,"avg_fare":22.761}},"avg_fare":27.1171,"avg_pay":21.5652,"avg_miles":7.209},{"h":7,"rides":12266,"boroughs":{"Manhattan":{"rides":3809,"avg_fare":33.692},"Brooklyn":{"rides":3128,"avg_fare":25.151},"Queens":{"rides":2999,"avg_fare":23.4182},"Bronx":{"rides":2107,"avg_fare":21.2142},"Staten Island":{"rides":222,"avg_fare":23.7189}},"avg_fare":29.3507,"avg_pay":23.7784,"avg_miles":6.1037},{"h":8,"rides":14633,"boroughs":{"Manhattan":{"rides":4658,"avg_fare":27.9508},"Brooklyn":{"rides":3739,"avg_fare":23.0098},"Queens":{"rides":3683,"avg_fare":22.3721},"Bronx":{"rides":2288,"avg_fare":18.9867},"Staten Island":{"rides":265,"avg_fare":18.592}},"avg_fare":22.1823,"avg_pay":18.5822,"avg_miles":5.5882},{"h":9,"rides":18184,"boroughs":{"Manhattan":{"rides":6051,"avg_fare":27.8151},"Brooklyn":{"rides":4804,"avg_fare":20.9278},"Queens":{"rides":4330,"avg_fare":21.6174},"Bronx":{"rides":2698,"avg_fare":19.8683},"Staten Island":{"rides":301,"avg_fare":21.2928}},"avg_fare":22.3043,"avg_pay":18.7588,"avg_miles":5.3152},{"h":10,"rides":20605,"boroughs":{"Manhattan":{"rides":7275,"avg_fare":28.3824},"Brooklyn":{"rides":5377,"avg_fare":20.6516},"Queens":{"rides":4831,"avg_fare":22.4448},"Bronx":{"rides":2818,"avg_fare":19.9703},"Staten Island":{"rides":302,"avg_fare":21.3787}},"avg_fare":25.2946,"avg_pay":21.6089,"avg_miles":6.1374},{"h":11,"rides":21672,"boroughs":{"Manhattan":{"rides":7804,"avg_fare":31.3051},"Brooklyn":{"rides":5827,"avg_fare":21.9002},"Queens":{"rides":4848,"avg_fare":23.4168},"Bronx":{"rides":2841,"avg_fare":20.834},"Staten Island":{"rides":351,"avg_fare":24.4669}},"avg_fare":23.3338,"avg_pay":19.3392,"avg_miles":5.1663},{"h":12,"rides":22384,"boroughs":{"Manhattan":{"rides":7960,"avg_fare":31.7484},"Brooklyn":{"rides":6138,"avg_fare":21.8105},"Queens":{"rides":5017,"avg_fare":24.0126},"Bronx":{"rides":2921,"avg_fare":21.9097},"Staten Island":{"rides":348,"avg_fare":24.3503}},"avg_fare":24.7663,"avg_pay":21.0832,"avg_miles":5.3131},{"h":13,"rides":23406,"boroughs":{"Manhattan":{"rides":8319,"avg_fare":31.4086},"Brooklyn":{"rides":6365,"avg_fare":22.4832},"Queens":{"rides":5257,"avg_fare":23.5819},"Bronx":{"rides":3107,"avg_fare":21.4079},"Staten Island":{"rides":358,"avg_fare":23.9417}},"avg_fare":24.5647,"avg_pay":21.2501,"avg_miles":5.219},{"h":14,"rides":25439,"boroughs":{"Manhattan":{"rides":8533,"avg_fare":31.0765},"Brooklyn":{"rides":7068,"avg_fare":22.7645},"Queens":{"rides":5895,"avg_fare":23.6371},"Bronx":{"rides":3574,"avg_fare":22.1836},"Staten Island":{"rides":367,"avg_fare":21.7626}},"avg_fare":21.8741,"avg_pay":19.1026,"avg_miles":4.4917},{"h":15,"rides":26418,"boroughs":{"Manhattan":{"rides":8837,"avg_fare":29.312},"Brooklyn":{"rides":7595,"avg_fare":22.1178},"Queens":{"rides":5806,"avg_fare":23.2546},"Bronx":{"rides":3745,"avg_fare":22.7276},"Staten Island":{"rides":435,"avg_fare":21.7947}},"avg_fare":23.8413,"avg_pay":20.7402,"avg_miles":5.0116},{"h":16,"rides":27104,"boroughs":{"Manhattan":{"rides":9638,"avg_fare":28.0044},"Brooklyn":{"rides":7589,"avg_fare":21.9217},"Queens":{"rides":5726,"avg_fare":23.9398},"Bronx":{"rides":3760,"avg_fare":22.5875},"Staten Island":{"rides":391,"avg_fare":23.3365}},"avg_fare":23.958,"avg_pay":20.9176,"avg_miles":5.1448},{"h":17,"rides":28811,"boroughs":{"Manhattan":{"rides":10763,"avg_fare":27.1119},"Brooklyn":{"rides":8320,"avg_fare":22.0994},"Queens":{"rides":5673,"avg_fare":23.6771},"Bronx":{"rides":3655,"avg_fare":21.7019},"Staten Island":{"rides":399,"avg_fare":26.5171}},"avg_fare":25.2662,"avg_pay":22.1739,"avg_miles":5.8474},{"h":18,"rides":30210,"boroughs":{"Manhattan":{"rides":11378,"avg_fare":25.8027},"Brooklyn":{"rides":8751,"avg_fare":21.4607},"Queens":{"rides":5951,"avg_fare":23.5792},"Bronx":{"rides":3703,"avg_fare":21.154},"Staten Island":{"rides":426,"avg_fare":24.1223}},"avg_fare":22.1265,"avg_pay":19.051,"avg_miles":4.8307},{"h":19,"rides":30005,"boroughs":{"Manhattan":{"rides":11514,"avg_fare":24.7882},"Brooklyn":{"rides":8546,"avg_fare":20.9658},"Queens":{"rides":5894,"avg_fare":23.0832},"Bronx":{"rides":3697,"avg_fare":20.5947},"Staten Island":{"rides":352,"avg_fare":21.93}},"avg_fare":23.1486,"avg_pay":19.7547,"avg_miles":5.4378},{"h":20,"rides":30231,"boroughs":{"Manhattan":{"rides":11221,"avg_fare":24.1865},"Brooklyn":{"rides":8770,"avg_fare":20.5481},"Queens":{"rides":6007,"avg_fare":23.7761},"Bronx":{"rides":3818,"avg_fare":19.4656},"Staten Island":{"rides":413,"avg_fare":20.7959}},"avg_fare":23.3145,"avg_pay":22.591,"avg_miles":6.2409},{"h":21,"rides":30165,"boroughs":{"Manhattan":{"rides":11115,"avg_fare":24.7912},"Brooklyn":{"rides":8796,"avg_fare":21.3728},"Queens":{"rides":6001,"avg_fare":23.6427},"Bronx":{"rides":3862,"avg_fare":19.1785},"Staten Island":{"rides":389,"avg_fare":27.313}},"avg_fare":21.5364,"avg_pay":18.4647,"avg_miles":4.8857},{"h":22,"rides":32231,"boroughs":{"Manhattan":{"rides":12515,"avg_fare":25.6216},"Brooklyn":{"rides":9526,"avg_fare":22.8143},"Queens":{"rides":5928,"avg_fare":24.1817},"Bronx":{"rides":3908,"avg_fare":19.4825},"Staten Island":{"rides":354,"avg_fare":26.2466}},"avg_fare":23.6693,"avg_pay":20.6885,"avg_miles":5.6131},{"h":23,"rides":31713,"boroughs":{"Manhattan":{"rides":12258,"avg_fare":26.6523},"Brooklyn":{"rides":9506,"avg_fare":22.9166},"Queens":{"rides":5786,"avg_fare":23.6912},"Bronx":{"rides":3800,"avg_fare":19.2779},"Staten Island":{"rides":363,"avg_fare":27.8172}},"avg_fare":24.0711,"avg_pay":20.8511,"avg_miles":5.6798}]}