{"date":"2024-06-26","hours":[{"h":0,"rides":14093,"boroughs":{"Manhattan":{"rides":6081,"avg_fare":26.1428},"Brooklyn":{"rides":3211,"avg_fare":17.8309},"Queens":{"rides":3081,"avg_fare":30.127},"Bronx":{"rides":1561,"avg_fare":15.6223},"Staten Island":{"rides":159,"avg_fare":18.4339}},"avg_fare":23.8677,"avg_pay":19.9098,"avg_miles":5.76,"avg_trip_time":1064.1435},{"h":1,"rides":8566,"boroughs":{"Manhattan":{"rides":3978,"avg_fare":23.8647},"Brooklyn":{"rides":1978,"avg_fare":17.9906},"Queens":{"rides":1626,"avg_fare":23.9953},"Bronx":{"rides":894,"avg_fare":15.485},"Staten Island":{"rides":90,"avg_fare":17.6382}},"avg_fare":21.5931,"avg_pay":18.0138,"avg_miles":5.3453,"avg_trip_time":962.0207},{"h":2,"rides":5441,"boroughs":{"Manhattan":{"rides":2333,"avg_fare":25.355},"Brooklyn":{"rides":1288,"avg_fare":18.414},"Queens":{"rides":1163,"avg_fare":23.1645},"Bronx":{"rides":603,"avg_fare":17.381},"Staten Island":{"rides":54,"avg_fare":23.8656}},"avg_fare":22.3452,"avg_pay":18.4039,"avg_miles":5.7976,"avg_trip_time":960.2029},{"h":3,"rides":4611,"boroughs":{"Manhattan":{"rides":1793,"avg_fare":27.7024},"Brooklyn":{"rides":1091,"avg_fare":22.0845},"Queens":{"rides":1081,"avg_fare":23.4187},"Bronx":{"rides":592,"avg_fare":20.3677},"Staten Island":{"rides":54,"avg_fare":24.93}},"avg_fare":24.3947,"avg_pay":20.1215,"avg_miles":6.6781,"avg_trip_time":1011.0536},{"h":4,"rides":5821,"boroughs":{"Manhattan":{"rides":2008,"avg_fare":37.765},"Brooklyn":{"rides":1454,"avg_fare":26.7986},"Queens":{"rides":1523,"avg_fare":22.8449},"Bronx":{"rides":755,"avg_fare":21.5976},"Staten Island":{"rides":81,"avg_fare":28.4081}},"avg_fare":28.8949,"avg_pay":23.2282,"avg_miles":7.8914,"avg_trip_time":1094.7416},{"h":5,"rides":8848,"boroughs":{"Manhattan":{"rides":2821,"avg_fare":38.2332},"Brooklyn":{"rides":2254,"avg_fare":27.2125},"Queens":{"rides":2336,"avg_fare":23.7479},"Bronx":{"rides":1270,"avg_fare":20.7956},"Staten Island":{"rides":167,"avg_fare":26.0028}},"avg_fare":28.8676,"avg_pay":23.0839,"avg_miles":7.5929,"avg_trip_time":1140.3901},{"h":6,"rides":14617,"boroughs":{"Manhattan":{"rides":4858,"avg_fare":30.4421},"Brooklyn":{"rides":3589,"avg_fare":25.8001},"Queens":{"rides":3591,"avg_fare":26.7101},"Bronx":{"rides":2327,"avg_fare":20.2292},"Staten Island":{"rides":251,"avg_fare":22.8423}},"avg_fare":26.6282,"avg_pay":21.216,"avg_miles":6.282,"avg_trip_time":1170.9},{"h":7,"rides":23701,"boroughs":{"Manhattan":{"rides":7833,"avg_fare":27.8929},"Brooklyn":{"rides":5706,"avg_fare":24.3374},"Queens":{"rides":5514,"avg_fare":25.983},"Bronx":{"rides":4191,"avg_fare":19.0538},"Staten Island":{"rides":456,"avg_fare":21.227}},"avg_fare":24.901,"avg_pay":19.5022,"avg_miles":4.8698,"avg_trip_time":1176.1423},{"h":8,"rides":30416,"boroughs":{"Manhattan":{"rides":10936,"avg_fare":30.334},"Brooklyn":{"rides":7110,"avg_fare":24.7973},"Queens":{"rides":6583,"avg_fare":25.5544},"Bronx":{"rides":5202,"avg_fare":18.2724},"Staten Island":{"rides":584,"avg_fare":19.7724}},"avg_fare":25.7397,"avg_pay":19.7596,"avg_miles":4.4484,"avg_trip_time":1201.9019},{"h":9,"rides":27419,"boroughs":{"Manhattan":{"rides":10567,"avg_fare":29.1908},"Brooklyn":{"rides":6664,"avg_fare":22.4565},"Queens":{"rides":5648,"avg_fare":26.6857},"Bronx":{"rides":4050,"avg_fare":17.9793},"Staten Island":{"rides":490,"avg_fare":20.0923}},"avg_fare":25.2194,"avg_pay":19.9784,"avg_miles":4.5073,"avg_trip_time":1230.8356},{"h":10,"rides":22815,"boroughs":{"Manhattan":{"rides":8562,"avg_fare":30.965},"Brooklyn":{"rides":5672,"avg_fare":22.6341},"Queens":{"rides":5047,"avg_fare":29.1893},"Bronx":{"rides":3139,"avg_fare":18.9215},"Staten Island":{"rides":395,"avg_fare":23.294}},"avg_fare":26.7112,"avg_pay":21.0965,"avg_miles":4.8608,"avg_trip_time":1325.8451},{"h":11,"rides":22151,"boroughs":{"Manhattan":{"rides":8547,"avg_fare":33.1736},"Brooklyn":{"rides":5580,"avg_fare":22.478},"Queens":{"rides":4592,"avg_fare":30.9053},"Bronx":{"rides":3002,"avg_fare":20.1559},"Staten Island":{"rides":430,"avg_fare":22.2411}},"avg_fare":28.0326,"avg_pay":21.574,"avg_miles":4.8487,"avg_trip_time":1363.2159},{"h":12,"rides":22040,"boroughs":{"Manhattan":{"rides":8597,"avg_fare":35.8356},"Brooklyn":{"rides":5494,"avg_fare":23.505},"Queens":{"rides":4466,"avg_fare":30.3854},"Bronx":{"rides":3073,"avg_fare":19.5729},"Staten Island":{"rides":410,"avg_fare":22.1296}},"avg_fare":29.1351,"avg_pay":22.6825,"avg_miles":4.9263,"avg_trip_time":1443.3533},{"h":13,"rides":22460,"boroughs":{"Manhattan":{"rides":8465,"avg_fare":38.5803},"Brooklyn":{"rides":5603,"avg_fare":24.2131},"Queens":{"rides":4772,"avg_fare":30.2739},"Bronx":{"rides":3203,"avg_fare":20.0681},"Staten Island":{"rides":416,"avg_fare":19.4757}},"avg_fare":30.2366,"avg_pay":23.3055,"avg_miles":4.9791,"avg_trip_time":1485.1427},{"h":14,"rides":24776,"boroughs":{"Manhattan":{"rides":8616,"avg_fare":40.9404},"Brooklyn":{"rides":6476,"avg_fare":24.5036},"Queens":{"rides":5579,"avg_fare":30.8519},"Bronx":{"rides":3570,"avg_fare":21.1166},"Staten Island":{"rides":532,"avg_fare":20.7267}},"avg_fare":31.0786,"avg_pay":24.14,"avg_miles":4.7913,"avg_trip_time":1563.8503},{"h":15,"rides":24425,"boroughs":{"Manhattan":{"rides":8357,"avg_fare":43.0522},"Brooklyn":{"rides":6499,"avg_fare":23.9147},"Queens":{"rides":5473,"avg_fare":34.6522},"Bronx":{"rides":3585,"avg_fare":21.6552},"Staten Island":{"rides":510,"avg_fare":21.6455}},"avg_fare":32.4898,"avg_pay":25.2263,"avg_miles":4.8093,"avg_trip_time":1653.5473},{"h":16,"rides":24893,"boroughs":{"Manhattan":{"rides":8644,"avg_fare":43.7205},"Brooklyn":{"rides":6750,"avg_fare":22.2713},"Queens":{"rides":5537,"avg_fare":33.8251},"Bronx":{"rides":3448,"avg_fare":20.125},"Staten Island":{"rides":511,"avg_fare":19.7607}},"avg_fare":31.9409,"avg_pay":25.1296,"avg_miles":4.713,"avg_trip_time":1640.7967},{"h":17,"rides":27281,"boroughs":{"Manhattan":{"rides":9607,"avg_fare":43.655},"Brooklyn":{"rides":7500,"avg_fare":22.0384},"Queens":{"rides":5939,"avg_fare":30.3071},"Bronx":{"rides":3708,"avg_fare":19.6338},"Staten Island":{"rides":526,"avg_fare":21.1955}},"avg_fare":31.1078,"avg_pay":24.3773,"avg_miles":4.5057,"avg_trip_time":1552.2691},{"h":18,"rides":29126,"boroughs":{"Manhattan":{"rides":11830,"avg_fare":36.1261},"Brooklyn":{"rides":7632,"avg_fare":20.6335},"Queens":{"rides":5845,"avg_fare":28.1561},"Bronx":{"rides":3353,"avg_fare":17.8004},"Staten Island":{"rides":465,"avg_fare":18.7348}},"avg_fare":28.0792,"avg_pay":22.1909,"avg_miles":4.3551,"avg_trip_time":1365.9377},{"h":19,"rides":28181,"boroughs":{"Manhattan":{"rides":12601,"avg_fare":29.5851},"Brooklyn":{"rides":7010,"avg_fare":19.4559},"Queens":{"rides":5231,"avg_fare":28.5203},"Bronx":{"rides":2955,"avg_fare":16.8398},"Staten Island":{"rides":384,"avg_fare":18.3961}},"avg_fare":25.3789,"avg_pay":20.5094,"avg_miles":4.7233,"avg_trip_time":1258.5087},{"h":20,"rides":29921,"boroughs":{"Manhattan":{"rides":13658,"avg_fare":41.5462},"Brooklyn":{"rides":7850,"avg_fare":21.1085},"Queens":{"rides":5032,"avg_fare":27.3354},"Bronx":{"rides":3007,"avg_fare":17.218},"Staten Island":{"rides":372,"avg_fare":18.6955}},"avg_fare":31.064,"avg_pay":23.45,"avg_miles":5.0109,"avg_trip_time":1261.8048},{"h":21,"rides":32135,"boroughs":{"Manhattan":{"rides":14456,"avg_fare":53.5683},"Brooklyn":{"rides":8216,"avg_fare":21.6026},"Queens":{"rides":5746,"avg_fare":28.5579},"Bronx":{"rides":3404,"avg_fare":17.5747},"Staten Island":{"rides":312,"avg_fare":20.5989}},"avg_fare":36.7899,"avg_pay":26.5928,"avg_miles":5.3531,"avg_trip_time":1214.6758},{"h":22,"rides":27440,"boroughs":{"Manhattan":{"rides":12794,"avg_fare":40.2291},"Brooklyn":{"rides":7123,"avg_fare":20.9576},"Queens":{"rides":4448,"avg_fare":29.8636},"Bronx":{"rides":2781,"avg_fare":16.8493},"Staten Island":{"rides":292,"avg_fare":18.6676}},"avg_fare":30.9453,"avg_pay":23.0821,"avg_miles":5.7942,"avg_trip_time":1173.3259},{"h":23,"rides":23834,"boroughs":{"Manhattan":{"rides":10125,"avg_fare":36.3487},"Brooklyn":{"rides":6280,"avg_fare":21.2011},"Queens":{"rides":4456,"avg_fare":32.3785},"Bronx":{"rides":2728,"avg_fare":16.0356},"Staten Island":{"rides":245,"avg_fare":19.6283}},"avg_fare":29.1183,"avg_pay":22.453,"avg_miles":6.06,"avg_trip_time":1191.8127}]}